{
  "@type": "type.googleapis.com/google.cloud.connectors.v1.RuntimeEntitySchema",
  "entity": "1098T",
  "fields": [
    {
      "dataType": "DATA_TYPE_VARCHAR",
      "description": "Contains a unique identifier for an instance of an object.",
      "field": "_1098-T_Reference_WID",
      "key": true
    },
    {
      "dataType": "DATA_TYPE_VARCHAR",
      "description": "Contains a unique identifier for an instance of an object.",
      "field": "_1098-T_Reference__1098-T_ID",
      "nullable": true
    },
    {
      "dataType": "DATA_TYPE_VARCHAR",
      "description": "The reference ID for the 1098-T.",
      "field": "ID",
      "nullable": true
    },
    {
      "dataType": "DATA_TYPE_VARCHAR",
      "description": "Contains a unique identifier for an instance of an object.",
      "field": "Student_Reference_WID",
      "nullable": true
    },
    {
      "dataType": "DATA_TYPE_VARCHAR",
      "description": "Contains a unique identifier for an instance of an object.",
      "field": "Student_Reference_Academic_Person_ID",
      "nullable": true
    },
    {
      "dataType": "DATA_TYPE_VARCHAR",
      "description": "Contains a unique identifier for an instance of an object.",
      "field": "Student_Reference_Student_ID",
      "nullable": true
    },
    {
      "dataType": "DATA_TYPE_VARCHAR",
      "description": "Contains a unique identifier for an instance of an object.",
      "field": "Student_Reference_Universal_Identifier_ID",
      "nullable": true
    },
    {
      "dataType": "DATA_TYPE_VARCHAR",
      "description": "Contains a unique identifier for an instance of an object.",
      "field": "Academic_Unit_Reference_WID",
      "nullable": true
    },
    {
      "dataType": "DATA_TYPE_VARCHAR",
      "description": "Contains a unique identifier for an instance of an object.",
      "field": "Academic_Unit_Reference_Academic_Unit_ID",
      "nullable": true
    },
    {
      "dataType": "DATA_TYPE_VARCHAR",
      "description": "Contains a unique identifier for an instance of an object.",
      "field": "Calendar_Year_Reference_WID",
      "nullable": true
    },
    {
      "dataType": "DATA_TYPE_VARCHAR",
      "description": "Contains a unique identifier for an instance of an object.",
      "field": "Calendar_Year_Reference_Calendar_Year_ID",
      "nullable": true
    },
    {
      "dataType": "DATA_TYPE_BOOLEAN",
      "description": "True if this 1098-T marked for exclusion from Mass Printing, the 1098-T Outbound file, and all Student Self-Service 1098-T tasks.",
      "field": "Exclude_1098-T",
      "nullable": true
    },
    {
      "dataType": "DATA_TYPE_BOOLEAN",
      "description": "Corrected",
      "field": "Corrected",
      "nullable": true
    },
    {
      "dataType": "DATA_TYPE_BOOLEAN",
      "description": "A boolean indicating whether the user has done his/her due diligence for this 1098-T",
      "field": "Due_Diligence",
      "nullable": true
    },
    {
      "dataType": "DATA_TYPE_BOOLEAN",
      "description": "Override Remove from Printing Consent",
      "field": "Override_Remove_from_Printing_Consent",
      "nullable": true
    },
    {
      "dataType": "DATA_TYPE_BOOLEAN",
      "description": "A boolean indicating whether the user has given e-filing consent for this 1098-T",
      "field": "Student_Consent",
      "nullable": true
    },
    {
      "dataType": "DATA_TYPE_VARCHAR",
      "description": "The Account Number/Service Provider for this 1098-T.",
      "field": "Account_Number_Service_Provider",
      "nullable": true
    },
    {
      "dataType": "DATA_TYPE_DECIMAL",
      "description": "The 1098-T Box 1 value.",
      "field": "Box_1",
      "nullable": true
    },
    {
      "dataType": "DATA_TYPE_DECIMAL",
      "description": "The 1098-T Box 1 override value",
      "field": "Box_1_Override",
      "nullable": true
    },
    {
      "dataType": "DATA_TYPE_BOOLEAN",
      "description": "True if the Box 1 value was overridden for this 1098-T.",
      "field": "Box_1_Is_Overridden",
      "nullable": true
    },
    {
      "dataType": "DATA_TYPE_DECIMAL",
      "description": "The 1098-T Box 2 override value",
      "field": "Box_2_Override",
      "nullable": true
    },
    {
      "dataType": "DATA_TYPE_BOOLEAN",
      "description": "The 1098-T Box 3 override value",
      "field": "Box_3_Override",
      "nullable": true
    },
    {
      "dataType": "DATA_TYPE_DECIMAL",
      "description": "The 1098-T Box 4 value.",
      "field": "Box_4",
      "nullable": true
    },
    {
      "dataType": "DATA_TYPE_DECIMAL",
      "description": "The 1098-T Box 4 override value",
      "field": "Box_4_Override",
      "nullable": true
    },
    {
      "dataType": "DATA_TYPE_BOOLEAN",
      "description": "True if the Box 4 value was overridden for this 1098-T.",
      "field": "Box_4_Is_Overridden",
      "nullable": true
    },
    {
      "dataType": "DATA_TYPE_DECIMAL",
      "description": "The 1098-T Box 5 value.",
      "field": "Box_5",
      "nullable": true
    },
    {
      "dataType": "DATA_TYPE_DECIMAL",
      "description": "The 1098-T Box 5 override value",
      "field": "Box_5_Override",
      "nullable": true
    },
    {
      "dataType": "DATA_TYPE_BOOLEAN",
      "description": "True if the Box 5 value was overridden for this 1098-T.",
      "field": "Box_5_Is_Overridden",
      "nullable": true
    },
    {
      "dataType": "DATA_TYPE_DECIMAL",
      "description": "The 1098-T Box 6 value.",
      "field": "Box_6",
      "nullable": true
    },
    {
      "dataType": "DATA_TYPE_DECIMAL",
      "description": "The 1098-T Box 6 override value",
      "field": "Box_6_Override",
      "nullable": true
    },
    {
      "dataType": "DATA_TYPE_BOOLEAN",
      "description": "True if the Box 6 value was overridden for this 1098-T.",
      "field": "Box_6_Is_Overridden",
      "nullable": true
    },
    {
      "dataType": "DATA_TYPE_BOOLEAN",
      "description": "The 1098-T Box 7 value.",
      "field": "Box_7",
      "nullable": true
    },
    {
      "dataType": "DATA_TYPE_BOOLEAN",
      "description": "The 1098-T Box 7 override value",
      "field": "Box_7_Override",
      "nullable": true
    },
    {
      "dataType": "DATA_TYPE_BOOLEAN",
      "description": "True if the Box 7 value was overridden for this 1098-T.",
      "field": "Box_7_Is_Overridden",
      "nullable": true
    },
    {
      "dataType": "DATA_TYPE_BOOLEAN",
      "description": "The 1098-T Box 8 value.",
      "field": "Box_8",
      "nullable": true
    },
    {
      "dataType": "DATA_TYPE_BOOLEAN",
      "description": "The 1098-T Box 8 override value",
      "field": "Box_8_Override",
      "nullable": true
    },
    {
      "dataType": "DATA_TYPE_BOOLEAN",
      "description": "True if the Box 8 value was overridden for this 1098-T.",
      "field": "Box_8_Is_Overridden",
      "nullable": true
    },
    {
      "dataType": "DATA_TYPE_BOOLEAN",
      "description": "The 1098-T Box 9 value.",
      "field": "Box_9",
      "nullable": true
    },
    {
      "dataType": "DATA_TYPE_BOOLEAN",
      "description": "The 1098-T Box 9 override value",
      "field": "Box_9_Override",
      "nullable": true
    },
    {
      "dataType": "DATA_TYPE_BOOLEAN",
      "description": "True if the Box 9 value was overridden for this 1098-T.",
      "field": "Box_9_Is_Overridden",
      "nullable": true
    },
    {
      "dataType": "DATA_TYPE_DECIMAL",
      "description": "The 1098-T Box 10 overridden value.",
      "field": "Box_10_Overridden",
      "nullable": true
    },
    {
      "dataType": "DATA_TYPE_DECIMAL",
      "description": "The 1098-T Carryover value.",
      "field": "Carryover",
      "nullable": true
    },
    {
      "dataType": "DATA_TYPE_DECIMAL",
      "description": "The 1098-T Carryover override value",
      "field": "Carryover_Override",
      "nullable": true
    },
    {
      "dataType": "DATA_TYPE_BOOLEAN",
      "description": "True if the Carryover value was overridden for this 1098-T.",
      "field": "Carryover_Is_Overridden",
      "nullable": true
    },
    {
      "dataType": "DATA_TYPE_VARCHAR",
      "description": "Contains a unique identifier for an instance of an object.",
      "field": "Currency_Reference_WID",
      "nullable": true
    },
    {
      "dataType": "DATA_TYPE_VARCHAR",
      "description": "Contains a unique identifier for an instance of an object.",
      "field": "Currency_Reference_Currency_ID",
      "nullable": true
    },
    {
      "dataType": "DATA_TYPE_VARCHAR",
      "description": "Contains a unique identifier for an instance of an object.",
      "field": "Currency_Reference_Currency_Numeric_Code",
      "nullable": true
    },
    {
      "dataType": "DATA_TYPE_VARCHAR",
      "field": "Student_and_Institutional_Academic_Unit_and_Calendar_Year_Data_Prompt",
      "nullable": true
    }
  ],
  "jsonSchema": {
    "properties": {
      "Academic_Unit_Reference_Academic_Unit_ID": {
        "description": "Contains a unique identifier for an instance of an object.",
        "type": [
          "string",
          "null"
        ]
      },
      "Academic_Unit_Reference_WID": {
        "description": "Contains a unique identifier for an instance of an object.",
        "type": [
          "string",
          "null"
        ]
      },
      "Account_Number_Service_Provider": {
        "description": "The Account Number/Service Provider for this 1098-T.",
        "type": [
          "string",
          "null"
        ]
      },
      "Box_1": {
        "description": "The 1098-T Box 1 value.",
        "type": [
          "number",
          "null"
        ]
      },
      "Box_10_Overridden": {
        "description": "The 1098-T Box 10 overridden value.",
        "type": [
          "number",
          "null"
        ]
      },
      "Box_1_Is_Overridden": {
        "description": "True if the Box 1 value was overridden for this 1098-T.",
        "type": [
          "boolean",
          "null"
        ]
      },
      "Box_1_Override": {
        "description": "The 1098-T Box 1 override value",
        "type": [
          "number",
          "null"
        ]
      },
      "Box_2_Override": {
        "description": "The 1098-T Box 2 override value",
        "type": [
          "number",
          "null"
        ]
      },
      "Box_3_Override": {
        "description": "The 1098-T Box 3 override value",
        "type": [
          "boolean",
          "null"
        ]
      },
      "Box_4": {
        "description": "The 1098-T Box 4 value.",
        "type": [
          "number",
          "null"
        ]
      },
      "Box_4_Is_Overridden": {
        "description": "True if the Box 4 value was overridden for this 1098-T.",
        "type": [
          "boolean",
          "null"
        ]
      },
      "Box_4_Override": {
        "description": "The 1098-T Box 4 override value",
        "type": [
          "number",
          "null"
        ]
      },
      "Box_5": {
        "description": "The 1098-T Box 5 value.",
        "type": [
          "number",
          "null"
        ]
      },
      "Box_5_Is_Overridden": {
        "description": "True if the Box 5 value was overridden for this 1098-T.",
        "type": [
          "boolean",
          "null"
        ]
      },
      "Box_5_Override": {
        "description": "The 1098-T Box 5 override value",
        "type": [
          "number",
          "null"
        ]
      },
      "Box_6": {
        "description": "The 1098-T Box 6 value.",
        "type": [
          "number",
          "null"
        ]
      },
      "Box_6_Is_Overridden": {
        "description": "True if the Box 6 value was overridden for this 1098-T.",
        "type": [
          "boolean",
          "null"
        ]
      },
      "Box_6_Override": {
        "description": "The 1098-T Box 6 override value",
        "type": [
          "number",
          "null"
        ]
      },
      "Box_7": {
        "description": "The 1098-T Box 7 value.",
        "type": [
          "boolean",
          "null"
        ]
      },
      "Box_7_Is_Overridden": {
        "description": "True if the Box 7 value was overridden for this 1098-T.",
        "type": [
          "boolean",
          "null"
        ]
      },
      "Box_7_Override": {
        "description": "The 1098-T Box 7 override value",
        "type": [
          "boolean",
          "null"
        ]
      },
      "Box_8": {
        "description": "The 1098-T Box 8 value.",
        "type": [
          "boolean",
          "null"
        ]
      },
      "Box_8_Is_Overridden": {
        "description": "True if the Box 8 value was overridden for this 1098-T.",
        "type": [
          "boolean",
          "null"
        ]
      },
      "Box_8_Override": {
        "description": "The 1098-T Box 8 override value",
        "type": [
          "boolean",
          "null"
        ]
      },
      "Box_9": {
        "description": "The 1098-T Box 9 value.",
        "type": [
          "boolean",
          "null"
        ]
      },
      "Box_9_Is_Overridden": {
        "description": "True if the Box 9 value was overridden for this 1098-T.",
        "type": [
          "boolean",
          "null"
        ]
      },
      "Box_9_Override": {
        "description": "The 1098-T Box 9 override value",
        "type": [
          "boolean",
          "null"
        ]
      },
      "Calendar_Year_Reference_Calendar_Year_ID": {
        "description": "Contains a unique identifier for an instance of an object.",
        "type": [
          "string",
          "null"
        ]
      },
      "Calendar_Year_Reference_WID": {
        "description": "Contains a unique identifier for an instance of an object.",
        "type": [
          "string",
          "null"
        ]
      },
      "Carryover": {
        "description": "The 1098-T Carryover value.",
        "type": [
          "number",
          "null"
        ]
      },
      "Carryover_Is_Overridden": {
        "description": "True if the Carryover value was overridden for this 1098-T.",
        "type": [
          "boolean",
          "null"
        ]
      },
      "Carryover_Override": {
        "description": "The 1098-T Carryover override value",
        "type": [
          "number",
          "null"
        ]
      },
      "Corrected": {
        "description": "Corrected",
        "type": [
          "boolean",
          "null"
        ]
      },
      "Currency_Reference_Currency_ID": {
        "description": "Contains a unique identifier for an instance of an object.",
        "type": [
          "string",
          "null"
        ]
      },
      "Currency_Reference_Currency_Numeric_Code": {
        "description": "Contains a unique identifier for an instance of an object.",
        "type": [
          "string",
          "null"
        ]
      },
      "Currency_Reference_WID": {
        "description": "Contains a unique identifier for an instance of an object.",
        "type": [
          "string",
          "null"
        ]
      },
      "Due_Diligence": {
        "description": "A boolean indicating whether the user has done his/her due diligence for this 1098-T",
        "type": [
          "boolean",
          "null"
        ]
      },
      "Exclude_1098-T": {
        "description": "True if this 1098-T marked for exclusion from Mass Printing, the 1098-T Outbound file, and all Student Self-Service 1098-T tasks.",
        "type": [
          "boolean",
          "null"
        ]
      },
      "ID": {
        "description": "The reference ID for the 1098-T.",
        "type": [
          "string",
          "null"
        ]
      },
      "Override_Remove_from_Printing_Consent": {
        "description": "Override Remove from Printing Consent",
        "type": [
          "boolean",
          "null"
        ]
      },
      "Student_Consent": {
        "description": "A boolean indicating whether the user has given e-filing consent for this 1098-T",
        "type": [
          "boolean",
          "null"
        ]
      },
      "Student_Reference_Academic_Person_ID": {
        "description": "Contains a unique identifier for an instance of an object.",
        "type": [
          "string",
          "null"
        ]
      },
      "Student_Reference_Student_ID": {
        "description": "Contains a unique identifier for an instance of an object.",
        "type": [
          "string",
          "null"
        ]
      },
      "Student_Reference_Universal_Identifier_ID": {
        "description": "Contains a unique identifier for an instance of an object.",
        "type": [
          "string",
          "null"
        ]
      },
      "Student_Reference_WID": {
        "description": "Contains a unique identifier for an instance of an object.",
        "type": [
          "string",
          "null"
        ]
      },
      "Student_and_Institutional_Academic_Unit_and_Calendar_Year_Data_Prompt": {
        "type": [
          "string",
          "null"
        ]
      },
      "_1098-T_Reference_WID": {
        "description": "Contains a unique identifier for an instance of an object.",
        "type": [
          "string"
        ]
      },
      "_1098-T_Reference__1098-T_ID": {
        "description": "Contains a unique identifier for an instance of an object.",
        "type": [
          "string",
          "null"
        ]
      }
    },
    "type": [
      "object"
    ]
  },
  "operations": [
    "GET",
    "LIST"
  ]
}