{
  "@type": "type.googleapis.com/google.cloud.connectors.v1.RuntimeEntitySchema",
  "entity": "Appropriations_Appropriation_Snapshot_Data",
  "fields": [
    {
      "dataType": "DATA_TYPE_VARCHAR",
      "description": "The Reference ID of the Appropriation",
      "field": "Appropriation_Appropriation_Reference_ID",
      "nullable": true
    },
    {
      "dataType": "DATA_TYPE_DATE",
      "description": "The Date that the Appropriation Snapshot takes effect",
      "field": "Snapshot_Effective_Date",
      "nullable": true
    },
    {
      "dataType": "DATA_TYPE_VARCHAR",
      "description": "The Description of the Appropriation",
      "field": "Description",
      "nullable": true
    },
    {
      "dataType": "DATA_TYPE_DATE",
      "description": "The Start Date of the Appropriation",
      "field": "Start_Date",
      "nullable": true
    },
    {
      "dataType": "DATA_TYPE_DATE",
      "description": "The End Date of the Appropriation",
      "field": "End_Date",
      "nullable": true
    },
    {
      "dataType": "DATA_TYPE_VARCHAR",
      "description": "The Legislative Authority of the Appropriation",
      "field": "Legislative_Authority",
      "nullable": true
    },
    {
      "dataType": "DATA_TYPE_DATE",
      "description": "The Date that the Appropriation was Established",
      "field": "Date_Appropriation_Established",
      "nullable": true
    },
    {
      "dataType": "DATA_TYPE_VARCHAR",
      "description": "Contains a unique identifier for an instance of an object.",
      "field": "Appropriation_Type_Reference_WID",
      "nullable": true
    },
    {
      "dataType": "DATA_TYPE_VARCHAR",
      "description": "Contains a unique identifier for an instance of an object.",
      "field": "Appropriation_Type_Reference_Appropriation_Type",
      "nullable": true
    },
    {
      "dataType": "DATA_TYPE_DATE",
      "description": "The Date that the Appropriation Snapshot takes effect",
      "field": "Appropriation_Effective_Date_Prompt",
      "nullable": true
    }
  ],
  "jsonSchema": {
    "properties": {
      "Appropriation_Appropriation_Reference_ID": {
        "description": "The Reference ID of the Appropriation",
        "type": [
          "string",
          "null"
        ]
      },
      "Appropriation_Effective_Date_Prompt": {
        "description": "The Date that the Appropriation Snapshot takes effect",
        "type": [
          "string",
          "null"
        ]
      },
      "Appropriation_Type_Reference_Appropriation_Type": {
        "description": "Contains a unique identifier for an instance of an object.",
        "type": [
          "string",
          "null"
        ]
      },
      "Appropriation_Type_Reference_WID": {
        "description": "Contains a unique identifier for an instance of an object.",
        "type": [
          "string",
          "null"
        ]
      },
      "Date_Appropriation_Established": {
        "description": "The Date that the Appropriation was Established",
        "type": [
          "string",
          "null"
        ]
      },
      "Description": {
        "description": "The Description of the Appropriation",
        "type": [
          "string",
          "null"
        ]
      },
      "End_Date": {
        "description": "The End Date of the Appropriation",
        "type": [
          "string",
          "null"
        ]
      },
      "Legislative_Authority": {
        "description": "The Legislative Authority of the Appropriation",
        "type": [
          "string",
          "null"
        ]
      },
      "Snapshot_Effective_Date": {
        "description": "The Date that the Appropriation Snapshot takes effect",
        "type": [
          "string",
          "null"
        ]
      },
      "Start_Date": {
        "description": "The Start Date of the Appropriation",
        "type": [
          "string",
          "null"
        ]
      }
    },
    "type": [
      "object"
    ]
  },
  "operations": [
    "GET",
    "LIST"
  ]
}