[
  {
    "name": "ID",
    "type": "STRING",
    "mode": "REQUIRED"
  },
  {
    "name": "Calibration_Program_Name",
    "type": "STRING",
    "mode": "NULLABLE"
  },
  {
    "name": "Calibration_Program_Description",
    "type": "STRING",
    "mode": "NULLABLE"
  },
  {
    "name": "Program_Due_Date",
    "type": "STRING",
    "mode": "NULLABLE"
  },
  {
    "name": "Program_Status",
    "type": "BOOLEAN",
    "mode": "NULLABLE"
  },
  {
    "name": "Initiate_Population_Unplotted",
    "type": "BOOLEAN",
    "mode": "NULLABLE"
  },
  {
    "name": "Allow_update_of_Assess_Potential_during_Calibration",
    "type": "BOOLEAN",
    "mode": "NULLABLE"
  },
  {
    "name": "Autocomplete_First_Participant",
    "type": "BOOLEAN",
    "mode": "NULLABLE"
  },
  {
    "name": "Warning_on_Unplotted_Worker",
    "type": "BOOLEAN",
    "mode": "NULLABLE"
  },
  {
    "name": "Error_on_Unplotted_Worker",
    "type": "BOOLEAN",
    "mode": "NULLABLE"
  },
  {
    "name": "Warning_on_Target_Percentage_Population",
    "type": "BOOLEAN",
    "mode": "NULLABLE"
  },
  {
    "name": "Error_on_Target_Percentage_Population",
    "type": "BOOLEAN",
    "mode": "NULLABLE"
  },
  {
    "name": "nBox_Reference_WID",
    "type": "STRING",
    "mode": "NULLABLE"
  },
  {
    "name": "nBox_Reference_Custom_Report_ID",
    "type": "STRING",
    "mode": "NULLABLE"
  },
  {
    "name": "nBox_Cell_Limit",
    "type": "DECIMAL",
    "mode": "NULLABLE"
  },
  {
    "name": "Hide_nBox_Summary_View",
    "type": "BOOLEAN",
    "mode": "NULLABLE"
  },
  {
    "name": "Restricted_to_Rule_Reference_WID",
    "type": "STRING",
    "mode": "NULLABLE"
  },
  {
    "name": "Restricted_to_Rule_Reference_Calibration_Program_Rule_ID",
    "type": "STRING",
    "mode": "NULLABLE"
  },
  {
    "name": "Row_Default_Value_CRF_Reference_IID",
    "type": "STRING",
    "mode": "NULLABLE"
  },
  {
    "name": "Row_Default_Value_CRF_Reference_WID",
    "type": "STRING",
    "mode": "NULLABLE"
  },
  {
    "name": "Column_Default_Value_CRF_Reference_IID",
    "type": "STRING",
    "mode": "NULLABLE"
  },
  {
    "name": "Column_Default_Value_CRF_Reference_WID",
    "type": "STRING",
    "mode": "NULLABLE"
  },
  {
    "name": "Calibration_Value_Mapping",
    "type": "STRING",
    "mode": "NULLABLE"
  },
  {
    "name": "Cell_Target_Percentage_Data",
    "type": "STRING",
    "mode": "NULLABLE"
  }
]