[
  {
    "name": "Country_of_Registration_Reference_WID",
    "type": "STRING",
    "mode": "REQUIRED"
  },
  {
    "name": "Country_of_Registration_Reference_ISO_3166-1_Alpha-2_Code",
    "type": "STRING",
    "mode": "NULLABLE"
  },
  {
    "name": "Country_of_Registration_Reference_ISO_3166-1_Alpha-3_Code",
    "type": "STRING",
    "mode": "NULLABLE"
  },
  {
    "name": "Country_of_Registration_Reference_ISO_3166-1_Numeric-3_Code",
    "type": "STRING",
    "mode": "NULLABLE"
  },
  {
    "name": "Vehicle_ID",
    "type": "STRING",
    "mode": "NULLABLE"
  },
  {
    "name": "Vehicle_Registration",
    "type": "STRING",
    "mode": "NULLABLE"
  },
  {
    "name": "Date_First_Registered",
    "type": "STRING",
    "mode": "NULLABLE"
  },
  {
    "name": "Date_Vehicle_Terminated",
    "type": "STRING",
    "mode": "NULLABLE"
  },
  {
    "name": "Vehicle_Type_Reference_WID",
    "type": "STRING",
    "mode": "NULLABLE"
  },
  {
    "name": "Vehicle_Type_Reference_Company_Vehicle_Type",
    "type": "STRING",
    "mode": "NULLABLE"
  },
  {
    "name": "Model_Reference_WID",
    "type": "STRING",
    "mode": "NULLABLE"
  },
  {
    "name": "Model_Reference_Company_Vehicle_Model",
    "type": "STRING",
    "mode": "NULLABLE"
  },
  {
    "name": "Fuel_Type_Reference_WID",
    "type": "STRING",
    "mode": "NULLABLE"
  },
  {
    "name": "Fuel_Type_Reference_Vehicle_Fuel_Type_ID",
    "type": "STRING",
    "mode": "NULLABLE"
  },
  {
    "name": "Meet_Euro_Standard",
    "type": "BOOLEAN",
    "mode": "NULLABLE"
  },
  {
    "name": "CO2_Emissions",
    "type": "DECIMAL",
    "mode": "NULLABLE"
  },
  {
    "name": "Zero_Emissions_Mileage",
    "type": "DECIMAL",
    "mode": "NULLABLE"
  },
  {
    "name": "No_Approved_CO2_Emissions",
    "type": "BOOLEAN",
    "mode": "NULLABLE"
  },
  {
    "name": "Engine_Capacity",
    "type": "DECIMAL",
    "mode": "NULLABLE"
  },
  {
    "name": "Rotary_Engine",
    "type": "BOOLEAN",
    "mode": "NULLABLE"
  },
  {
    "name": "List_Price__including_VAT_",
    "type": "DECIMAL",
    "mode": "NULLABLE"
  },
  {
    "name": "Accessories_Price__including_VAT_",
    "type": "DECIMAL",
    "mode": "NULLABLE"
  }
]