[
  {
    "name": "CompensationPlan_Compensation_Plan_Reference_WID",
    "type": "STRING",
    "mode": "NULLABLE"
  },
  {
    "name": "Scorecard_Reference_WID",
    "type": "STRING",
    "mode": "NULLABLE"
  },
  {
    "name": "Scorecard_Reference_Performance_Scorecard_ID",
    "type": "STRING",
    "mode": "NULLABLE"
  },
  {
    "name": "Weight",
    "type": "DECIMAL",
    "mode": "NULLABLE"
  },
  {
    "name": "Bonus_Modifier_Reference_WID",
    "type": "STRING",
    "mode": "NULLABLE"
  },
  {
    "name": "Bonus_Modifier_Reference_Performance_Scorecard_ID",
    "type": "STRING",
    "mode": "NULLABLE"
  },
  {
    "name": "Plan_Type_Reference_WID_Prompt",
    "type": "STRING",
    "mode": "NULLABLE"
  },
  {
    "name": "Plan_Type_Reference_Compensation_Plan_Type_ID_Prompt",
    "type": "STRING",
    "mode": "NULLABLE"
  },
  {
    "name": "Include_Inactive_Prompt",
    "type": "BOOLEAN",
    "mode": "NULLABLE"
  }
]