{
  "@type": "type.googleapis.com/google.cloud.connectors.v1.RuntimeEntitySchema",
  "entity": "ContactConnections",
  "fields": [
    {
      "dataType": "DATA_TYPE_VARCHAR",
      "description": "Id for Worker Contact Connections",
      "field": "ID",
      "key": true
    },
    {
      "dataType": "DATA_TYPE_VARCHAR",
      "description": "Contains a unique identifier for an instance of an object.",
      "field": "Worker_Connection_Initiator_Reference_WID",
      "nullable": true
    },
    {
      "dataType": "DATA_TYPE_VARCHAR",
      "description": "Contains a unique identifier for an instance of an object.",
      "field": "Worker_Connection_Initiator_Reference_Contingent_Worker_ID",
      "nullable": true
    },
    {
      "dataType": "DATA_TYPE_VARCHAR",
      "description": "Contains a unique identifier for an instance of an object.",
      "field": "Worker_Connection_Initiator_Reference_Employee_ID",
      "nullable": true
    },
    {
      "dataType": "DATA_TYPE_VARCHAR",
      "description": "Contains a unique identifier for an instance of an object.",
      "field": "Worker_Connection_Reference_WID",
      "nullable": true
    },
    {
      "dataType": "DATA_TYPE_VARCHAR",
      "description": "Contains a unique identifier for an instance of an object.",
      "field": "Worker_Connection_Reference_Contingent_Worker_ID",
      "nullable": true
    },
    {
      "dataType": "DATA_TYPE_VARCHAR",
      "description": "Contains a unique identifier for an instance of an object.",
      "field": "Worker_Connection_Reference_Employee_ID",
      "nullable": true
    },
    {
      "dataType": "DATA_TYPE_DATE",
      "description": "The start date for the contact connection",
      "field": "Connection_Start_Date",
      "nullable": true
    },
    {
      "dataType": "DATA_TYPE_DATE",
      "description": "The end date for the contact connection",
      "field": "Connection_End_Date",
      "nullable": true
    }
  ],
  "jsonSchema": {
    "properties": {
      "Connection_End_Date": {
        "description": "The end date for the contact connection",
        "type": [
          "string",
          "null"
        ]
      },
      "Connection_Start_Date": {
        "description": "The start date for the contact connection",
        "type": [
          "string",
          "null"
        ]
      },
      "ID": {
        "description": "Id for Worker Contact Connections",
        "type": [
          "string"
        ]
      },
      "Worker_Connection_Initiator_Reference_Contingent_Worker_ID": {
        "description": "Contains a unique identifier for an instance of an object.",
        "type": [
          "string",
          "null"
        ]
      },
      "Worker_Connection_Initiator_Reference_Employee_ID": {
        "description": "Contains a unique identifier for an instance of an object.",
        "type": [
          "string",
          "null"
        ]
      },
      "Worker_Connection_Initiator_Reference_WID": {
        "description": "Contains a unique identifier for an instance of an object.",
        "type": [
          "string",
          "null"
        ]
      },
      "Worker_Connection_Reference_Contingent_Worker_ID": {
        "description": "Contains a unique identifier for an instance of an object.",
        "type": [
          "string",
          "null"
        ]
      },
      "Worker_Connection_Reference_Employee_ID": {
        "description": "Contains a unique identifier for an instance of an object.",
        "type": [
          "string",
          "null"
        ]
      },
      "Worker_Connection_Reference_WID": {
        "description": "Contains a unique identifier for an instance of an object.",
        "type": [
          "string",
          "null"
        ]
      }
    },
    "type": [
      "object"
    ]
  },
  "operations": [
    "GET",
    "LIST"
  ]
}