{
  "@type": "type.googleapis.com/google.cloud.connectors.v1.RuntimeEntitySchema",
  "entity": "DevelopmentItemStatus",
  "fields": [
    {
      "dataType": "DATA_TYPE_VARCHAR",
      "description": "ID for Development Item Status.",
      "field": "ID",
      "key": true
    },
    {
      "dataType": "DATA_TYPE_VARCHAR",
      "description": "Order for Development Item Status.",
      "field": "Order",
      "nullable": true
    },
    {
      "dataType": "DATA_TYPE_VARCHAR",
      "description": "Development Item Status Name.",
      "field": "Status",
      "nullable": true
    },
    {
      "dataType": "DATA_TYPE_VARCHAR",
      "description": "Contains a unique identifier for an instance of an object.",
      "field": "Maps_to_Workday_Status_Reference_WID",
      "nullable": true
    },
    {
      "dataType": "DATA_TYPE_VARCHAR",
      "description": "Contains a unique identifier for an instance of an object.",
      "field": "Maps_to_Workday_Status_Reference_Development_Item_Status",
      "nullable": true
    },
    {
      "dataType": "DATA_TYPE_BOOLEAN",
      "description": "Inactive Flag for Development Item Status.",
      "field": "Development_Item_Status_Inactive",
      "nullable": true
    }
  ],
  "jsonSchema": {
    "properties": {
      "Development_Item_Status_Inactive": {
        "description": "Inactive Flag for Development Item Status.",
        "type": [
          "boolean",
          "null"
        ]
      },
      "ID": {
        "description": "ID for Development Item Status.",
        "type": [
          "string"
        ]
      },
      "Maps_to_Workday_Status_Reference_Development_Item_Status": {
        "description": "Contains a unique identifier for an instance of an object.",
        "type": [
          "string",
          "null"
        ]
      },
      "Maps_to_Workday_Status_Reference_WID": {
        "description": "Contains a unique identifier for an instance of an object.",
        "type": [
          "string",
          "null"
        ]
      },
      "Order": {
        "description": "Order for Development Item Status.",
        "type": [
          "string",
          "null"
        ]
      },
      "Status": {
        "description": "Development Item Status Name.",
        "type": [
          "string",
          "null"
        ]
      }
    },
    "type": [
      "object"
    ]
  },
  "operations": [
    "GET",
    "LIST"
  ]
}