{
  "@type": "type.googleapis.com/google.cloud.connectors.v1.RuntimeEntitySchema",
  "entity": "IntercompanyCustomerContract",
  "fields": [
    {
      "dataType": "DATA_TYPE_VARCHAR",
      "description": "Reference ID for Intercompany contract.",
      "field": "ID",
      "key": true
    },
    {
      "dataType": "DATA_TYPE_VARCHAR",
      "description": "Contains a unique identifier for an instance of an object.",
      "field": "Company_Reference_WID",
      "nullable": true
    },
    {
      "dataType": "DATA_TYPE_VARCHAR",
      "description": "Contains a unique identifier for an instance of an object.",
      "field": "Company_Reference_Company_Reference_ID",
      "nullable": true
    },
    {
      "dataType": "DATA_TYPE_VARCHAR",
      "description": "Contains a unique identifier for an instance of an object.",
      "field": "Company_Reference_Organization_Reference_ID",
      "nullable": true
    },
    {
      "dataType": "DATA_TYPE_VARCHAR",
      "description": "Contains a unique identifier for an instance of an object.",
      "field": "Sold-To_Customer_Reference_WID",
      "nullable": true
    },
    {
      "dataType": "DATA_TYPE_VARCHAR",
      "description": "Contains a unique identifier for an instance of an object.",
      "field": "Sold-To_Customer_Reference_Customer_ID",
      "nullable": true
    },
    {
      "dataType": "DATA_TYPE_VARCHAR",
      "description": "Contains a unique identifier for an instance of an object.",
      "field": "Sold-To_Customer_Reference_Customer_Reference_ID",
      "nullable": true
    },
    {
      "dataType": "DATA_TYPE_VARCHAR",
      "description": "Contains a unique identifier for an instance of an object.",
      "field": "Sold-To_Customer_Reference_Sponsor_ID",
      "nullable": true
    },
    {
      "dataType": "DATA_TYPE_VARCHAR",
      "description": "Contains a unique identifier for an instance of an object.",
      "field": "Sold-To_Customer_Reference_Sponsor_Reference_ID",
      "nullable": true
    },
    {
      "dataType": "DATA_TYPE_VARCHAR",
      "description": "Contains a unique identifier for an instance of an object.",
      "field": "Sold-To_Customer_Reference_Student_Financial_Account_ID",
      "nullable": true
    },
    {
      "dataType": "DATA_TYPE_VARCHAR",
      "description": "Contains a unique identifier for an instance of an object.",
      "field": "Currency_Reference_WID",
      "nullable": true
    },
    {
      "dataType": "DATA_TYPE_VARCHAR",
      "description": "Contains a unique identifier for an instance of an object.",
      "field": "Currency_Reference_Currency_ID",
      "nullable": true
    },
    {
      "dataType": "DATA_TYPE_VARCHAR",
      "description": "Contains a unique identifier for an instance of an object.",
      "field": "Currency_Reference_Currency_Numeric_Code",
      "nullable": true
    },
    {
      "dataType": "DATA_TYPE_DATE",
      "description": "Document date for Intercompany Contract.",
      "field": "Effective_Date",
      "nullable": true
    },
    {
      "dataType": "DATA_TYPE_DATE",
      "description": "Contract Signed Date for Intercompany Contract.",
      "field": "Contract_Signed_Date",
      "nullable": true
    },
    {
      "dataType": "DATA_TYPE_VARCHAR",
      "description": "Contract Name for Intercompany Contract.",
      "field": "Contract_Name",
      "nullable": true
    },
    {
      "dataType": "DATA_TYPE_VARCHAR",
      "description": "Customer Contract Description for Intercompany Contract.",
      "field": "Contract_Description",
      "nullable": true
    },
    {
      "dataType": "DATA_TYPE_VARCHAR",
      "description": "Default Worktags for Intercompany Contract.",
      "field": "Default_Worktags_Reference",
      "nullable": true
    },
    {
      "dataType": "DATA_TYPE_VARCHAR",
      "description": "Customer Contract Intercompany Line Data for Intercompany Contract.",
      "field": "Intercompany_Customer_Contract_Line_Data",
      "nullable": true
    },
    {
      "dataType": "DATA_TYPE_VARCHAR",
      "description": "Customer in Request Criteria to Get Intercompany Contract.",
      "field": "Customer_Reference_WID_Prompt",
      "nullable": true
    },
    {
      "dataType": "DATA_TYPE_VARCHAR",
      "description": "Customer in Request Criteria to Get Intercompany Contract.",
      "field": "Customer_Reference_Customer_ID_Prompt",
      "nullable": true
    },
    {
      "dataType": "DATA_TYPE_VARCHAR",
      "description": "Customer in Request Criteria to Get Intercompany Contract.",
      "field": "Customer_Reference_Customer_Reference_ID_Prompt",
      "nullable": true
    },
    {
      "dataType": "DATA_TYPE_VARCHAR",
      "description": "Customer in Request Criteria to Get Intercompany Contract.",
      "field": "Customer_Reference_Sponsor_ID_Prompt",
      "nullable": true
    },
    {
      "dataType": "DATA_TYPE_VARCHAR",
      "description": "Customer in Request Criteria to Get Intercompany Contract.",
      "field": "Customer_Reference_Sponsor_Reference_ID_Prompt",
      "nullable": true
    },
    {
      "dataType": "DATA_TYPE_VARCHAR",
      "description": "Customer in Request Criteria to Get Intercompany Contract.",
      "field": "Customer_Reference_Student_Financial_Account_ID_Prompt",
      "nullable": true
    },
    {
      "dataType": "DATA_TYPE_VARCHAR",
      "description": "Company in Request Criteria to Get Intercompany Contract.",
      "field": "Company_Reference_WID_Prompt",
      "nullable": true
    },
    {
      "dataType": "DATA_TYPE_VARCHAR",
      "description": "Company in Request Criteria to Get Intercompany Contract.",
      "field": "Company_Reference_Company_Reference_ID_Prompt",
      "nullable": true
    },
    {
      "dataType": "DATA_TYPE_VARCHAR",
      "description": "Company in Request Criteria to Get Intercompany Contract.",
      "field": "Company_Reference_Organization_Reference_ID_Prompt",
      "nullable": true
    },
    {
      "dataType": "DATA_TYPE_DATE",
      "description": "Transaction Start Date in Request Criteria to Get Intercompany Contract.",
      "field": "Transaction_Date_Start_Date_Prompt",
      "nullable": true
    },
    {
      "dataType": "DATA_TYPE_DATE",
      "description": "Transaction End Date in Request Criteria to Get Intercompany Contract.",
      "field": "Transaction_Date_End_Date_Prompt",
      "nullable": true
    }
  ],
  "jsonSchema": {
    "properties": {
      "Company_Reference_Company_Reference_ID": {
        "description": "Contains a unique identifier for an instance of an object.",
        "type": [
          "string",
          "null"
        ]
      },
      "Company_Reference_Company_Reference_ID_Prompt": {
        "description": "Company in Request Criteria to Get Intercompany Contract.",
        "type": [
          "string",
          "null"
        ]
      },
      "Company_Reference_Organization_Reference_ID": {
        "description": "Contains a unique identifier for an instance of an object.",
        "type": [
          "string",
          "null"
        ]
      },
      "Company_Reference_Organization_Reference_ID_Prompt": {
        "description": "Company in Request Criteria to Get Intercompany Contract.",
        "type": [
          "string",
          "null"
        ]
      },
      "Company_Reference_WID": {
        "description": "Contains a unique identifier for an instance of an object.",
        "type": [
          "string",
          "null"
        ]
      },
      "Company_Reference_WID_Prompt": {
        "description": "Company in Request Criteria to Get Intercompany Contract.",
        "type": [
          "string",
          "null"
        ]
      },
      "Contract_Description": {
        "description": "Customer Contract Description for Intercompany Contract.",
        "type": [
          "string",
          "null"
        ]
      },
      "Contract_Name": {
        "description": "Contract Name for Intercompany Contract.",
        "type": [
          "string",
          "null"
        ]
      },
      "Contract_Signed_Date": {
        "description": "Contract Signed Date for Intercompany Contract.",
        "type": [
          "string",
          "null"
        ]
      },
      "Currency_Reference_Currency_ID": {
        "description": "Contains a unique identifier for an instance of an object.",
        "type": [
          "string",
          "null"
        ]
      },
      "Currency_Reference_Currency_Numeric_Code": {
        "description": "Contains a unique identifier for an instance of an object.",
        "type": [
          "string",
          "null"
        ]
      },
      "Currency_Reference_WID": {
        "description": "Contains a unique identifier for an instance of an object.",
        "type": [
          "string",
          "null"
        ]
      },
      "Customer_Reference_Customer_ID_Prompt": {
        "description": "Customer in Request Criteria to Get Intercompany Contract.",
        "type": [
          "string",
          "null"
        ]
      },
      "Customer_Reference_Customer_Reference_ID_Prompt": {
        "description": "Customer in Request Criteria to Get Intercompany Contract.",
        "type": [
          "string",
          "null"
        ]
      },
      "Customer_Reference_Sponsor_ID_Prompt": {
        "description": "Customer in Request Criteria to Get Intercompany Contract.",
        "type": [
          "string",
          "null"
        ]
      },
      "Customer_Reference_Sponsor_Reference_ID_Prompt": {
        "description": "Customer in Request Criteria to Get Intercompany Contract.",
        "type": [
          "string",
          "null"
        ]
      },
      "Customer_Reference_Student_Financial_Account_ID_Prompt": {
        "description": "Customer in Request Criteria to Get Intercompany Contract.",
        "type": [
          "string",
          "null"
        ]
      },
      "Customer_Reference_WID_Prompt": {
        "description": "Customer in Request Criteria to Get Intercompany Contract.",
        "type": [
          "string",
          "null"
        ]
      },
      "Default_Worktags_Reference": {
        "description": "Default Worktags for Intercompany Contract.",
        "type": [
          "string",
          "null"
        ]
      },
      "Effective_Date": {
        "description": "Document date for Intercompany Contract.",
        "type": [
          "string",
          "null"
        ]
      },
      "ID": {
        "description": "Reference ID for Intercompany contract.",
        "type": [
          "string"
        ]
      },
      "Intercompany_Customer_Contract_Line_Data": {
        "description": "Customer Contract Intercompany Line Data for Intercompany Contract.",
        "type": [
          "string",
          "null"
        ]
      },
      "Sold-To_Customer_Reference_Customer_ID": {
        "description": "Contains a unique identifier for an instance of an object.",
        "type": [
          "string",
          "null"
        ]
      },
      "Sold-To_Customer_Reference_Customer_Reference_ID": {
        "description": "Contains a unique identifier for an instance of an object.",
        "type": [
          "string",
          "null"
        ]
      },
      "Sold-To_Customer_Reference_Sponsor_ID": {
        "description": "Contains a unique identifier for an instance of an object.",
        "type": [
          "string",
          "null"
        ]
      },
      "Sold-To_Customer_Reference_Sponsor_Reference_ID": {
        "description": "Contains a unique identifier for an instance of an object.",
        "type": [
          "string",
          "null"
        ]
      },
      "Sold-To_Customer_Reference_Student_Financial_Account_ID": {
        "description": "Contains a unique identifier for an instance of an object.",
        "type": [
          "string",
          "null"
        ]
      },
      "Sold-To_Customer_Reference_WID": {
        "description": "Contains a unique identifier for an instance of an object.",
        "type": [
          "string",
          "null"
        ]
      },
      "Transaction_Date_End_Date_Prompt": {
        "description": "Transaction End Date in Request Criteria to Get Intercompany Contract.",
        "type": [
          "string",
          "null"
        ]
      },
      "Transaction_Date_Start_Date_Prompt": {
        "description": "Transaction Start Date in Request Criteria to Get Intercompany Contract.",
        "type": [
          "string",
          "null"
        ]
      }
    },
    "type": [
      "object"
    ]
  },
  "operations": [
    "GET",
    "LIST"
  ]
}