{
  "@type": "type.googleapis.com/google.cloud.connectors.v1.RuntimeEntitySchema",
  "entity": "PayrollPayeeRTIs",
  "fields": [
    {
      "dataType": "DATA_TYPE_VARCHAR",
      "description": "Reference ID for Worker RTI Data",
      "field": "ID",
      "key": true
    },
    {
      "dataType": "DATA_TYPE_VARCHAR",
      "description": "Contains a unique identifier for an instance of an object.",
      "field": "Worker_Reference_WID",
      "nullable": true
    },
    {
      "dataType": "DATA_TYPE_VARCHAR",
      "description": "Contains a unique identifier for an instance of an object.",
      "field": "Worker_Reference_Contingent_Worker_ID",
      "nullable": true
    },
    {
      "dataType": "DATA_TYPE_VARCHAR",
      "description": "Contains a unique identifier for an instance of an object.",
      "field": "Worker_Reference_Employee_ID",
      "nullable": true
    },
    {
      "dataType": "DATA_TYPE_DATE",
      "description": "Effective as of Date",
      "field": "Effective_As_Of",
      "nullable": true
    },
    {
      "dataType": "DATA_TYPE_VARCHAR",
      "description": "Contains a unique identifier for an instance of an object.",
      "field": "Company_Reference_WID",
      "nullable": true
    },
    {
      "dataType": "DATA_TYPE_VARCHAR",
      "description": "Contains a unique identifier for an instance of an object.",
      "field": "Company_Reference_Company_Reference_ID",
      "nullable": true
    },
    {
      "dataType": "DATA_TYPE_VARCHAR",
      "description": "Contains a unique identifier for an instance of an object.",
      "field": "Company_Reference_Organization_Reference_ID",
      "nullable": true
    },
    {
      "dataType": "DATA_TYPE_BOOLEAN",
      "description": "Irregular payment pattern indicator",
      "field": "Irregular_Payment_Pattern",
      "nullable": true
    },
    {
      "dataType": "DATA_TYPE_VARCHAR",
      "description": "Contains a unique identifier for an instance of an object.",
      "field": "Late_PAYE_Reporting_Reason_Reference_WID",
      "nullable": true
    },
    {
      "dataType": "DATA_TYPE_VARCHAR",
      "description": "Contains a unique identifier for an instance of an object.",
      "field": "Late_PAYE_Reporting_Reason_Reference_Payroll_Constant_Text_ID",
      "nullable": true
    },
    {
      "dataType": "DATA_TYPE_BOOLEAN",
      "description": "FPS has been submitted for the deceased worker.",
      "field": "FPS_Submitted_for_Deceased_Worker",
      "nullable": true
    },
    {
      "dataType": "DATA_TYPE_BOOLEAN",
      "description": "Override Contract End Date flag",
      "field": "Override_Contract_End_Date",
      "nullable": true
    },
    {
      "dataType": "DATA_TYPE_DATE",
      "description": "Contract End Date",
      "field": "Contract_End_Date",
      "nullable": true
    },
    {
      "dataType": "DATA_TYPE_VARCHAR",
      "description": "Payroll Payee RTI Request Worker. Supports multiple values.",
      "field": "Worker_Reference_WID_Prompt",
      "nullable": true
    },
    {
      "dataType": "DATA_TYPE_VARCHAR",
      "description": "Payroll Payee RTI Request Worker. Supports multiple values.",
      "field": "Worker_Reference_Contingent_Worker_ID_Prompt",
      "nullable": true
    },
    {
      "dataType": "DATA_TYPE_VARCHAR",
      "description": "Payroll Payee RTI Request Worker. Supports multiple values.",
      "field": "Worker_Reference_Employee_ID_Prompt",
      "nullable": true
    },
    {
      "dataType": "DATA_TYPE_VARCHAR",
      "description": "Payroll Payee RTI Request Companies. Supports multiple values.",
      "field": "Company_Reference_WID_Prompt",
      "nullable": true
    },
    {
      "dataType": "DATA_TYPE_VARCHAR",
      "description": "Payroll Payee RTI Request Companies. Supports multiple values.",
      "field": "Company_Reference_Company_Reference_ID_Prompt",
      "nullable": true
    },
    {
      "dataType": "DATA_TYPE_VARCHAR",
      "description": "Payroll Payee RTI Request Companies. Supports multiple values.",
      "field": "Company_Reference_Organization_Reference_ID_Prompt",
      "nullable": true
    },
    {
      "dataType": "DATA_TYPE_DATE",
      "description": "Payroll Payee RTI Request Effective Date",
      "field": "Effective_As_Of_Prompt",
      "nullable": true
    }
  ],
  "jsonSchema": {
    "properties": {
      "Company_Reference_Company_Reference_ID": {
        "description": "Contains a unique identifier for an instance of an object.",
        "type": [
          "string",
          "null"
        ]
      },
      "Company_Reference_Company_Reference_ID_Prompt": {
        "description": "Payroll Payee RTI Request Companies. Supports multiple values.",
        "type": [
          "string",
          "null"
        ]
      },
      "Company_Reference_Organization_Reference_ID": {
        "description": "Contains a unique identifier for an instance of an object.",
        "type": [
          "string",
          "null"
        ]
      },
      "Company_Reference_Organization_Reference_ID_Prompt": {
        "description": "Payroll Payee RTI Request Companies. Supports multiple values.",
        "type": [
          "string",
          "null"
        ]
      },
      "Company_Reference_WID": {
        "description": "Contains a unique identifier for an instance of an object.",
        "type": [
          "string",
          "null"
        ]
      },
      "Company_Reference_WID_Prompt": {
        "description": "Payroll Payee RTI Request Companies. Supports multiple values.",
        "type": [
          "string",
          "null"
        ]
      },
      "Contract_End_Date": {
        "description": "Contract End Date",
        "type": [
          "string",
          "null"
        ]
      },
      "Effective_As_Of": {
        "description": "Effective as of Date",
        "type": [
          "string",
          "null"
        ]
      },
      "Effective_As_Of_Prompt": {
        "description": "Payroll Payee RTI Request Effective Date",
        "type": [
          "string",
          "null"
        ]
      },
      "FPS_Submitted_for_Deceased_Worker": {
        "description": "FPS has been submitted for the deceased worker.",
        "type": [
          "boolean",
          "null"
        ]
      },
      "ID": {
        "description": "Reference ID for Worker RTI Data",
        "type": [
          "string"
        ]
      },
      "Irregular_Payment_Pattern": {
        "description": "Irregular payment pattern indicator",
        "type": [
          "boolean",
          "null"
        ]
      },
      "Late_PAYE_Reporting_Reason_Reference_Payroll_Constant_Text_ID": {
        "description": "Contains a unique identifier for an instance of an object.",
        "type": [
          "string",
          "null"
        ]
      },
      "Late_PAYE_Reporting_Reason_Reference_WID": {
        "description": "Contains a unique identifier for an instance of an object.",
        "type": [
          "string",
          "null"
        ]
      },
      "Override_Contract_End_Date": {
        "description": "Override Contract End Date flag",
        "type": [
          "boolean",
          "null"
        ]
      },
      "Worker_Reference_Contingent_Worker_ID": {
        "description": "Contains a unique identifier for an instance of an object.",
        "type": [
          "string",
          "null"
        ]
      },
      "Worker_Reference_Contingent_Worker_ID_Prompt": {
        "description": "Payroll Payee RTI Request Worker. Supports multiple values.",
        "type": [
          "string",
          "null"
        ]
      },
      "Worker_Reference_Employee_ID": {
        "description": "Contains a unique identifier for an instance of an object.",
        "type": [
          "string",
          "null"
        ]
      },
      "Worker_Reference_Employee_ID_Prompt": {
        "description": "Payroll Payee RTI Request Worker. Supports multiple values.",
        "type": [
          "string",
          "null"
        ]
      },
      "Worker_Reference_WID": {
        "description": "Contains a unique identifier for an instance of an object.",
        "type": [
          "string",
          "null"
        ]
      },
      "Worker_Reference_WID_Prompt": {
        "description": "Payroll Payee RTI Request Worker. Supports multiple values.",
        "type": [
          "string",
          "null"
        ]
      }
    },
    "type": [
      "object"
    ]
  },
  "operations": [
    "GET",
    "LIST"
  ]
}