[
  {
    "name": "ID",
    "type": "STRING",
    "mode": "REQUIRED"
  },
  {
    "name": "Submit",
    "type": "BOOLEAN",
    "mode": "NULLABLE"
  },
  {
    "name": "Transaction_End_Date",
    "type": "STRING",
    "mode": "NULLABLE"
  },
  {
    "name": "Percent_Complete_Method_Reference_WID",
    "type": "STRING",
    "mode": "NULLABLE"
  },
  {
    "name": "Percent_Complete_Method_Reference_Percent_Complete_Method_ID",
    "type": "STRING",
    "mode": "NULLABLE"
  },
  {
    "name": "Percent_Complete_Status_Reference_WID",
    "type": "STRING",
    "mode": "NULLABLE"
  },
  {
    "name": "Percent_Complete_Status_Reference_Document_Status_ID",
    "type": "STRING",
    "mode": "NULLABLE"
  },
  {
    "name": "Billable_Project_Reference_WID",
    "type": "STRING",
    "mode": "NULLABLE"
  },
  {
    "name": "Billable_Project_Reference_Project_ID",
    "type": "STRING",
    "mode": "NULLABLE"
  },
  {
    "name": "Contract_Value",
    "type": "DECIMAL",
    "mode": "NULLABLE"
  },
  {
    "name": "Percent_Complete_Line_Data",
    "type": "STRING",
    "mode": "NULLABLE"
  },
  {
    "name": "Forecast_Snapshot_Reference_WID",
    "type": "STRING",
    "mode": "NULLABLE"
  },
  {
    "name": "Forecast_Snapshot_Reference_Resource_Forecast_ID",
    "type": "STRING",
    "mode": "NULLABLE"
  },
  {
    "name": "Estimated_Hours_to_Complete",
    "type": "DECIMAL",
    "mode": "NULLABLE"
  },
  {
    "name": "Cumulative_Hours_Worked",
    "type": "DECIMAL",
    "mode": "NULLABLE"
  },
  {
    "name": "Estimated_Cost",
    "type": "DECIMAL",
    "mode": "NULLABLE"
  },
  {
    "name": "Actual_Cost",
    "type": "DECIMAL",
    "mode": "NULLABLE"
  },
  {
    "name": "Actual_Percent_Complete",
    "type": "DECIMAL",
    "mode": "NULLABLE"
  },
  {
    "name": "Currency_Reference_WID",
    "type": "STRING",
    "mode": "NULLABLE"
  },
  {
    "name": "Currency_Reference_Currency_ID",
    "type": "STRING",
    "mode": "NULLABLE"
  },
  {
    "name": "Currency_Reference_Currency_Numeric_Code",
    "type": "STRING",
    "mode": "NULLABLE"
  },
  {
    "name": "Company_Reference_WID",
    "type": "STRING",
    "mode": "NULLABLE"
  },
  {
    "name": "Company_Reference_Company_Reference_ID",
    "type": "STRING",
    "mode": "NULLABLE"
  },
  {
    "name": "Company_Reference_Organization_Reference_ID",
    "type": "STRING",
    "mode": "NULLABLE"
  },
  {
    "name": "Note",
    "type": "STRING",
    "mode": "NULLABLE"
  },
  {
    "name": "Set_Actual_Percent_Complete_to_Zero",
    "type": "BOOLEAN",
    "mode": "NULLABLE"
  },
  {
    "name": "As_Of_Date_Reference_IID_Prompt",
    "type": "STRING",
    "mode": "NULLABLE"
  },
  {
    "name": "As_Of_Date_Reference_WID_Prompt",
    "type": "STRING",
    "mode": "NULLABLE"
  }
]