{
  "@type": "type.googleapis.com/google.cloud.connectors.v1.RuntimeEntitySchema",
  "entity": "WaitlistorDeferDecisionStatuses",
  "fields": [
    {
      "dataType": "DATA_TYPE_VARCHAR",
      "description": "The reference to the existing Student Application",
      "field": "ID",
      "key": true
    },
    {
      "dataType": "DATA_TYPE_VARCHAR",
      "description": "Contains a unique identifier for an instance of an object.",
      "field": "Admission_Decision_Reference_WID",
      "nullable": true
    },
    {
      "dataType": "DATA_TYPE_VARCHAR",
      "description": "Contains a unique identifier for an instance of an object.",
      "field": "Admission_Decision_Reference_Admission_Decision_ID",
      "nullable": true
    },
    {
      "dataType": "DATA_TYPE_VARCHAR",
      "description": "Contains a unique identifier for an instance of an object.",
      "field": "Admission_Decision_Reason_Reference_WID",
      "nullable": true
    },
    {
      "dataType": "DATA_TYPE_VARCHAR",
      "description": "Contains a unique identifier for an instance of an object.",
      "field": "Admission_Decision_Reason_Reference_Admission_Decision_Reason_ID",
      "nullable": true
    }
  ],
  "jsonSchema": {
    "properties": {
      "Admission_Decision_Reason_Reference_Admission_Decision_Reason_ID": {
        "description": "Contains a unique identifier for an instance of an object.",
        "type": [
          "string",
          "null"
        ]
      },
      "Admission_Decision_Reason_Reference_WID": {
        "description": "Contains a unique identifier for an instance of an object.",
        "type": [
          "string",
          "null"
        ]
      },
      "Admission_Decision_Reference_Admission_Decision_ID": {
        "description": "Contains a unique identifier for an instance of an object.",
        "type": [
          "string",
          "null"
        ]
      },
      "Admission_Decision_Reference_WID": {
        "description": "Contains a unique identifier for an instance of an object.",
        "type": [
          "string",
          "null"
        ]
      },
      "ID": {
        "description": "The reference to the existing Student Application",
        "type": [
          "string"
        ]
      }
    },
    "type": [
      "object"
    ]
  },
  "operations": [
    "GET",
    "LIST"
  ]
}